ctp_builder/__init__.py
ctp_builder/cli.py
ctp_builder/helpers.py
ctp_builder/project.py
ctp_builder/stages.py
ctp_builder/version.py
ctp_builder/resources/config/default.yaml
ctp_builder/resources/config/dicom_organizer.yaml
ctp_builder/resources/config/passthrough.yaml
ctp_builder/resources/scripts/BurnedInPixelsFilter.script
ctp_builder/resources/scripts/ContrastAnonymizer.script
ctp_builder/resources/scripts/DicomAnonymizer.script
ctp_builder/resources/scripts/DicomFilter.script
ctp_builder/resources/scripts/DicomPixelAnonymizer.script
ctp_builder/resources/scripts/HealthCheckFilter.script
ctp_builder/resources/scripts/ModalityFilter.script
ctp_builder/resources/scripts/SeriesDescriptionBlacklist.script
ctp_builder/resources/scripts/XNATSpecifier.script
ctp_builder/resources/templates/anonymizer.xml
ctp_builder/resources/templates/config.xml
ctp_builder/resources/templates/corrector.xml
ctp_builder/resources/templates/default_pipeline_template.xml
ctp_builder/resources/templates/exporter.xml
ctp_builder/resources/templates/filter.xml
ctp_builder/resources/templates/idmap.xml
ctp_builder/resources/templates/import.xml
ctp_builder/resources/templates/objecttracker.xml
ctp_builder/resources/templates/pixelanonymizer.xml
ctp_builder/resources/templates/tablechecker.xml
ctp_builder/resources/templates/projects/contrast2.yaml
ctp_builder/resources/templates/projects/full_service.yaml
ctp_builder/resources/templates/projects/network_service.yaml
ctp_builder/resources/templates/projects/passthrough_service.yaml
ctp_builder/resources/templates/projects/passthrough_service_healthcheck.yaml
ctp_builder-1.0.1.dist-info/METADATA
ctp_builder-1.0.1.dist-info/WHEEL
ctp_builder-1.0.1.dist-info/entry_points.txt
ctp_builder-1.0.1.dist-info/licenses/LICENSE
ctp_builder-1.0.1.dist-info/RECORD
