Metadata-Version: 2.4
Name: ctp-builder
Version: 1.0.1
Project-URL: CI/CD, https://gitlab.com/radiology/infrastructure/data-curation-tools/ctp-builder/-/pipelines
Project-URL: Changelog, https://ctp-builder.readthedocs.io/en/latest/changelog.html
Project-URL: Documentation, https://ctp-builder.readthedocs.io
Project-URL: Download, https://gitlab.com/radiology/infrastructure/data-curation-tools/ctp-builder/-/archive/master/ctp-builder-master.zip
Project-URL: Homepage, https://gitlab.com/radiology/infrastructure/data-curation-tools/ctp-builder
Project-URL: Issues, https://gitlab.com/radiology/infrastructure/data-curation-tools/ctp-builder/-/issues
Author: Ivan Bocharov, Adriaan Versteeg, Hakim Achterberg
License: Copyright 2024 Biomedical Imaging Group Rotterdam, Department of
License-File: LICENSE
Requires-Python: >=3.9
Requires-Dist: click-loglevel
Requires-Dist: click>=8.1.0
Requires-Dist: jinja2
Requires-Dist: pytest
Requires-Dist: pyyaml==6.0.2
Requires-Dist: requests
